pumpp/__init__.py
pumpp/base.py
pumpp/core.py
pumpp/exceptions.py
pumpp/labels.py
pumpp/sampler.py
pumpp/version.py
pumpp/feature/__init__.py
pumpp/feature/_utils.py
pumpp/feature/base.py
pumpp/feature/cqt.py
pumpp/feature/fft.py
pumpp/feature/mel.py
pumpp/feature/rhythm.py
pumpp/feature/time.py
pumpp/task/__init__.py
pumpp/task/base.py
pumpp/task/beat.py
pumpp/task/chord.py
pumpp/task/key.py
pumpp/task/regression.py
pumpp/task/structure.py
pumpp/task/tags.py
pumpp-0.6.0.dist-info/LICENSE.md
pumpp-0.6.0.dist-info/METADATA
pumpp-0.6.0.dist-info/WHEEL
pumpp-0.6.0.dist-info/top_level.txt
pumpp-0.6.0.dist-info/RECORD
