Metadata-Version: 2.1
Name: pumpp
Version: 0.6.0
Summary: A practically universal music pre-processor
Home-page: https://github.com/bmcfee/pumpp
Author: Brian McFee
License: ISC
Project-URL: Source, https://github.com/bmcfee/pumpp
Project-URL: Download, https://github.com/bmcfee/pumpp/releases
Platform: UNKNOWN
Classifier: License :: OSI Approved :: ISC License (ISCL)
Classifier: Programming Language :: Python
Classifier: Development Status :: 3 - Alpha
Classifier: Intended Audience :: Developers
Classifier: Topic :: Software Development
Classifier: Programming Language :: Python :: 3
Classifier: Programming Language :: Python :: 3.7
Classifier: Programming Language :: Python :: 3.8
Classifier: Programming Language :: Python :: 3.9
Requires-Python: >=3.6
License-File: LICENSE.md
Requires-Dist: librosa (>=0.8.0)
Requires-Dist: jams (>=0.3)
Requires-Dist: scikit-learn (>=1.0)
Requires-Dist: mir-eval (>=0.5)
Provides-Extra: docs
Requires-Dist: numpydoc ; extra == 'docs'
Requires-Dist: sphinx ; extra == 'docs'
Provides-Extra: keras
Requires-Dist: keras (>=2.6) ; extra == 'keras'
Provides-Extra: tests
Requires-Dist: pytest ; extra == 'tests'
Requires-Dist: pytest-cov ; extra == 'tests'
Requires-Dist: keras (>=2.6) ; extra == 'tests'
Requires-Dist: tensorflow (>=2.0) ; extra == 'tests'
